hpcparse/ConfigOptions.py
hpcparse/NodeType.py
hpcparse/PartitionType.py
hpcparse/__init__.py
hpcparse/accountingparser.py
hpcparse/accounts.py
hpcparse/accountsparser.py
hpcparse/cluster.py
hpcparse/clusterparser.py
hpcparse/job.py
hpcparse/qos.py
hpcparse/qosparser.py
hpcparse/slurmconfparser.py
hpcparse/user.py
hpcparse/userparser.py
hpcparse-0.1.44.dist-info/LICENSE
hpcparse-0.1.44.dist-info/METADATA
hpcparse-0.1.44.dist-info/WHEEL
hpcparse-0.1.44.dist-info/top_level.txt
hpcparse-0.1.44.dist-info/zip-safe
hpcparse-0.1.44.dist-info/RECORD
