Metadata-Version: 2.1
Name: hpcparse
Version: 0.1.44
Summary: Parse HPC data like users, accounting, accounts, qos, ... etc
Home-page: https://github.com/brdalert/hpcparse
Author: Brandon Dunn
Author-email: brandondunn_21@yahoo.com
License: UNKNOWN
Project-URL: Documentation, https://github.com/brdalert/hpcparse
Keywords: HPC parser
Platform: UNKNOWN
Classifier: Development Status :: 4 - Beta
Classifier: Environment :: Console
Classifier: Intended Audience :: System Administrators
Classifier: License :: OSI Approved :: GNU General Public License v3 or later (GPLv3+)
Classifier: Operating System :: POSIX :: Linux
Classifier: Programming Language :: Python :: 3.6
Classifier: Programming Language :: Python :: 3.7
Classifier: Programming Language :: Python :: 3.8
Classifier: Programming Language :: Python :: 3.9
Requires-Python: >=3.4
Provides-Extra: docs
Requires-Dist: sphinx ; extra == 'docs'
